<?xml version="1.0" encoding="UTF-8"?>

<!-- generated on 2021-07-20 11:24:15 by Eclipse SUMO netedit Version 1.9.2
<configuration xmlns:xsi="http://www.w3.org/2001/XMLSchema-instance" xsi:noNamespaceSchemaLocation="http://sumo.dlr.de/xsd/netconvertConfiguration.xsd">

    <input>
        <sumo-net-file value="./env/merge/network.net.xml"/>
    </input>

    <output>
        <output-file value="./env/merge/network.net.xml"/>
    </output>

    <processing>
        <geometry.min-radius.fix.railways value="false"/>
        <geometry.max-grade.fix value="false"/>
        <offset.disable-normalization value="true"/>
        <lefthand value="false"/>
    </processing>

    <junctions>
        <no-turnarounds value="true"/>
        <junctions.corner-detail value="5"/>
        <junctions.limit-turn-speed value="5.5"/>
        <rectangular-lane-cut value="true"/>
    </junctions>

    <pedestrian>
        <walkingareas value="false"/>
    </pedestrian>

    <netedit>
        <route-files value="C:\Users\achaveza\OneDrive%20-%20MathWorks\Documents\codes\itn-school\HighwayEnvironment\env\merge\vehiclesRoutes.rou.xml"/>
    </netedit>

    <report>
        <aggregate-warnings value="5"/>
    </report>

</configuration>
-->

<routes xmlns:xsi="http://www.w3.org/2001/XMLSchema-instance" xsi:noNamespaceSchemaLocation="http://sumo.dlr.de/xsd/routes_file.xsd">
    <route edges="3.0.00 -2.0.00" color="128,0,0" id="route_merge"/>
    <route edges="1.0.00 -2.0.00" color="yellow" id="route_straight"/>
</routes>
